apinum/__init__.py
apinum/apinum.py
apinum/well_number_to_state_county.json
apinum/well_numbers.json
apinum-0.1.8.dist-info/METADATA
apinum-0.1.8.dist-info/WHEEL
apinum-0.1.8.dist-info/entry_points.txt
apinum-0.1.8.dist-info/top_level.txt
apinum-0.1.8.dist-info/RECORD
