Metadata-Version: 2.1
Name: apinum
Version: 0.1.8
Project-URL: homepage, https://github.com/bzlmnop/apinum
Keywords: US Well Numbers,API Numbers,Well Numbers,apinum
Requires-Python: >=3.7
